{
    "TPHO*UF/O": [
        "nouveau",
        "nouveaux"
    ],
    "T*": [
        "t'",
        "t",
        "te",
        "techno"
    ],
    "TPHO*EUR": [
        "noir",
        "noire"
    ],
    "SHER/*EU": [
        "chéri",
        "chérie"
    ],
    "S*UR": [
        "sûr",
        "sure",
        "sûre"
    ],
    "AE/PH*EU": [
        "ami",
        "amie"
    ],
    "APL/*EU": [
        "ami",
        "amie"
    ],
    "AO*": [
        "eux",
        "e",
        "euh"
    ],
    "TPH*U": [
        "nu",
        "nues",
        "nue"
    ],
    "TPH*UL": [
        "nul",
        "nulle"
    ],
    "SA*PB": [
        "sans",
        "cents",
        "cent"
    ],
    "*EU": [
        "y",
        "i"
    ],
    "S*EUPB": [
        "sein",
        "sain",
        "saint",
        "seing",
        "ceint"
    ],
    "HR*": [
        "l'",
        "l"
    ],
    "*EUFRPB/OB/U": [
        "inconnu",
        "inconnue"
    ],
    "*EUPB/KOB/U": [
        "inconnu",
        "inconnue"
    ],
    "TPAO*": [
        "feu",
        "feue",
        "feux"
    ],
    "PWHRO*PB": [
        "ballon",
        "blond",
        "belon"
    ],
    "W*EUPB": [
        "vin",
        "vain",
        "vingt",
        "vins"
    ],
    "KREU/KH*FL": [
        "criminel",
        "criminelle"
    ],
    "PW*EUPB": [
        "bain",
        "ben"
    ],
    "A*EUP/APG/OL": [
        "espagnol",
        "espagnole"
    ],
    "PHAPBT/O*E": [
        "manteau",
        "mentaux",
        "manteaux"
    ],
    "HR*EG/AL": [
        "illégal",
        "légale",
        "illégale"
    ],
    "PART/*EU": [
        "partie",
        "parti"
    ],
    "AEUB/PH*EU": [
        "ennemi",
        "ennemie"
    ],
    "SEUF/*EUL": [
        "civil",
        "civile"
    ],
    "PROFL/AEUGZ/*FL": [
        "professionnel",
        "professionnelle"
    ],
    "PR*EU": [
        "pourri",
        "pris",
        "pourrie",
        "péri",
        "périe",
        "pairie",
        "paierie"
    ],
    "TKPWRA*EUBG": [
        "grec",
        "grecque"
    ],
    "KHRA*EUR": [
        "clair",
        "éclair",
        "claire",
        "clerc",
        "éclaire",
        "scalaire"
    ],
    "HR*EUR": [
        "lire",
        "élire",
        "lyre"
    ],
    "OR/EUG/*EUPBL": [
        "original",
        "originale"
    ],
    "SO*EU": [
        "soit",
        "soie",
        "soi"
    ],
    "S*EU": [
        "si",
        "ci",
        "psy",
        "scie",
        "sis",
        "psi",
        "cis"
    ],
    "*E": [
        "et",
        "ais",
        "eh",
        "é"
    ],
    "PH*UR": [
        "mur",
        "mûre",
        "mûr"
    ],
    "TK*EUP/AR/U": [
        "disparu",
        "disparue"
    ],
    "KR*EU": [
        "cri",
        "écrit",
        "kerrie"
    ],
    "SO*E": [
        "saut",
        "seaux",
        "seau",
        "sceau",
        "sceaux"
    ],
    "PREUPBS/*EUP/AL": [
        "principal",
        "principale"
    ],
    "TPHAZ/*EU": [
        "nazi",
        "nazie"
    ],
    "PHO*RLGTS": [
        "mortel",
        "mortelle"
    ],
    "PHORT/*FL": [
        "mortel",
        "mortelle"
    ],
    "KAP/*EUT/AL": [
        "capitale",
        "capital"
    ],
    "AB/RUT/*EU": [
        "abruti",
        "abrutie"
    ],
    "AE/PWRUT/*EU": [
        "abruti",
        "abrutie"
    ],
    "PHAB/*UFL": [
        "manuel",
        "manuelle"
    ],
    "A*EUR": [
        "air",
        "aire",
        "ère",
        "ers",
        "erre"
    ],
    "TK*": [
        "d'",
        "d"
    ],
    "WHA*L": [
        "final",
        "finale"
    ],
    "EUPBT/HRAEUBGT/W*FL": [
        "intellectuel",
        "intellectuelle"
    ],
    "SPWHRAEUBGT/W*FL": [
        "intellectuel",
        "intellectuelle"
    ],
    "PO*EUL": [
        "poil",
        "poli",
        "poêle",
        "polie",
        "poly"
    ],
    "KOUFP/*E": [
        "coucher",
        "couché"
    ],
    "PA*EU": [
        "paix",
        "pet",
        "paie",
        "spahi"
    ],
    "HR*UTS": [
        "lutz",
        "lustre",
        "illustre"
    ],
    "TPHO*RPL/AL": [
        "normal",
        "normale"
    ],
    "TK*UR": [
        "dur",
        "dure"
    ],
    "RA*": [
        "ya",
        "ra",
        "ras",
        "raz"
    ],
    "WO*E": [
        "veau",
        "vaux",
        "veaux",
        "vau"
    ],
    "SKRA*EUT": [
        "secrète",
        "concrète",
        "charrette"
    ],
    "KHRA*PB": [
        "clan",
        "collant"
    ],
    "S*EUR": [
        "sir",
        "sire",
        "cire"
    ],
    "O*EBLG": [
        "auquel",
        "auxquels",
        "auxquelles"
    ],
    "TKPWA*EU": [
        "gay",
        "guet",
        "gaie"
    ],
    "SA*": [
        "sa",
        "sas",
        "çà"
    ],
    "PHATS/TPH*FL": [
        "maternel",
        "maternelle"
    ],
    "KOBG/*U": [
        "cocu",
        "cocue"
    ],
    "*FGD/U": [
        "vendu",
        "vendue"
    ],
    "SPWUFT/R*LZ/-FL": [
        "industriel",
        "industrielle"
    ],
    "PWA*LZ": [
        "bye",
        "balise",
        "bail",
        "baille"
    ],
    "PAPBD/*U": [
        "pendu",
        "pendue"
    ],
    "OFL/EUS/*EUFL": [
        "officiel",
        "officielle"
    ],
    "HR*EUS": [
        "lis",
        "lys",
        "lisse",
        "lice",
        "ellipse"
    ],
    "HR*E": [
        "aller",
        "lé",
        "allez",
        "ailé"
    ],
    "PUS/O*E": [
        "puceau",
        "puceaux"
    ],
    "PHA*T": [
        "mat",
        "mat'",
        "mate",
        "math",
        "matte"
    ],
    "AB/O*E": [
        "anneau",
        "anaux",
        "anneaux"
    ],
    "AE/TPHO*E": [
        "anneau",
        "anaux",
        "anneaux"
    ],
    "PWA*EPB/WHU": [
        "bienvenue",
        "bienvenu"
    ],
    "*TS/PHEUPBL": [
        "terminal",
        "terminale"
    ],
    "W*EUFL": [
        "vif",
        "vielle"
    ],
    "PA*EUR": [
        "paire",
        "pair",
        "pers"
    ],
    "PR*": [
        "paire",
        "pair",
        "pers"
    ],
    "KO*UT": [
        "scout",
        "scoute"
    ],
    "HRAO*EU": [
        "lieu",
        "lieue",
        "lieux"
    ],
    "SHR*R": [
        "saler",
        "seller",
        "sceller",
        "celer"
    ],
    "RA*EUB": [
        "reine",
        "renne",
        "rêne"
    ],
    "T*URBG": [
        "turc",
        "turque"
    ],
    "KRA*ER": [
        "crier",
        "écrier",
        "courrier"
    ],
    "*BGS/TRAT/RAEUTS": [
        "extraterrestre",
        "extra-terrestre"
    ],
    "KP*T/RAT/RAEUTS": [
        "extraterrestre",
        "extra-terrestre"
    ],
    "TPH*E": [
        "nez",
        "ney",
        "né"
    ],
    "HR*/WE": [
        "lever",
        "loué",
        "levé"
    ],
    "W*EUPB/KU": [
        "vaincu",
        "vaincue"
    ],
    "SA*EUB": [
        "scène",
        "sahib",
        "saine",
        "sen",
        "seine",
        "senne",
        "cène"
    ],
    "STK*T/TPHU": [
        "détenu",
        "détenue"
    ],
    "KAU/EU/A*EUR": [
        "cuillère",
        "écuyère",
        "cuiller"
    ],
    "PWAT/*U": [
        "battu",
        "battue"
    ],
    "PHAB/*EUFL": [
        "manif",
        "manivelle"
    ],
    "PWAEUFT/EU/O*E": [
        "bestiau",
        "bestiaux"
    ],
    "PWR*EUBG": [
        "brique",
        "brick",
        "bourrique"
    ],
    "TRA*EU": [
        "trait",
        "trahie",
        "trahi"
    ],
    "KA*R": [
        "car",
        "care",
        "écart",
        "carre",
        "quarre"
    ],
    "PHUT/W*FL": [
        "mutuel",
        "mutuelle"
    ],
    "STK*U": [
        "dessus",
        "déçue"
    ],
    "HOR/*EUZ/OFL/RPT/AL": [
        "horizontal",
        "horizontale"
    ],
    "KR*U": [
        "cru",
        "crue",
        "écru",
        "écrue"
    ],
    "R*EUFL": [
        "rival",
        "rivale",
        "riff",
        "riel",
        "rifle",
        "rif"
    ],
    "AB/O*RPL/AL": [
        "anormal",
        "anormale"
    ],
    "A*E/TPHORPL/AL": [
        "anormal",
        "anormale"
    ],
    "TA*EPB": [
        "tiens",
        "tien"
    ],
    "O*EU": [
        "ouah",
        "wouah",
        "oie",
        "oye"
    ],
    "SKRA*EU": [
        "secret",
        "concret"
    ],
    "*BGS/KHRU": [
        "exclu",
        "exclue"
    ],
    "KP*BG/HRU": [
        "exclu",
        "exclue"
    ],
    "KO*EPB/TAPB": [
        "content",
        "comptant"
    ],
    "PW*EUT": [
        "bite",
        "bit",
        "beat",
        "bitte"
    ],
    "T*UB": [
        "tube",
        "tune",
        "thune"
    ],
    "*EUPL/ORLGTS": [
        "immortel",
        "immortelle"
    ],
    "EUPL/ORT/*FL": [
        "immortel",
        "immortelle"
    ],
    "HR*U": [
        "élu",
        "lu",
        "élue",
        "lue",
        "lut"
    ],
    "PHART/*EUR": [
        "martyr",
        "martyre"
    ],
    "RO*BG": [
        "rock",
        "roque",
        "roc"
    ],
    "PWO*UL/O": [
        "boulot",
        "bouleaux",
        "bouleau"
    ],
    "SKR*T": [
        "secteur",
        "charte",
        "charité"
    ],
    "TPHA*Z": [
        "naze",
        "nase"
    ],
    "SHR*E": [
        "salé",
        "scellé"
    ],
    "KPWO*EUL": [
        "impoli",
        "embolie",
        "impolie"
    ],
    "HRA*EU": [
        "laid",
        "lai",
        "let",
        "lei",
        "lez",
        "laie",
        "lès"
    ],
    "PAO*EU": [
        "pieu",
        "pieux"
    ],
    "R*L/ABGS": [
        "relax",
        "relaxe"
    ],
    "WHR*U": [
        "voulu",
        "velu",
        "voulue",
        "velue"
    ],
    "EUPBG/*EB/U": [
        "ingénu",
        "ingénue"
    ],
    "TA*LZ": [
        "taille",
        "thaïe",
        "thaï"
    ],
    "KHA*ER": [
        "minier",
        "meunier",
        "minière",
        "meunière"
    ],
    "A*E/R": [
        "art",
        "ars",
        "are"
    ],
    "A*R": [
        "art",
        "ars",
        "are"
    ],
    "OBGS/*EUD/APBT/AL": [
        "occidental",
        "occidentale"
    ],
    "PWA*EU": [
        "baie",
        "bai",
        "bey"
    ],
    "OD/EU/OEF/*EUZ/UFL": [
        "audio-visuelle",
        "audiovisuelle",
        "audiovisuel",
        "audio-visuel"
    ],
    "TPAEUFT/*EUFL": [
        "festival",
        "festif"
    ],
    "HR*EU": [
        "lit",
        "lie",
        "li"
    ],
    "P*EU": [
        "pis",
        "pie",
        "pi",
        "spi"
    ],
    "HRA*PB": [
        "lent",
        "allant",
        "élan"
    ],
    "SAPBT/*EUPL/APBT/AL": [
        "sentimental",
        "sentimentale"
    ],
    "ST*EUPL/APBT/AL": [
        "sentimental",
        "sentimentale"
    ],
    "T*EUPB": [
        "teint",
        "tain",
        "thym",
        "tin"
    ],
    "RAPB/KA*R": [
        "rencard",
        "rancart",
        "rancard"
    ],
    "PWHRABL/A*": [
        "bla bla",
        "blabla",
        "bla-bla"
    ],
    "T*E": [
        "thé",
        "té"
    ],
    "KHRO*R": [
        "éclore",
        "chlore",
        "clore"
    ],
    "HRA*BG": [
        "lac",
        "laque",
        "lacs",
        "lack"
    ],
    "AE/P*BL": [
        "anal",
        "annales",
        "anale"
    ],
    "A*PBL": [
        "anal",
        "annales",
        "anale"
    ],
    "OR/A*EPBT/AL": [
        "oriental",
        "orientale"
    ],
    "SKWR*T/E": [
        "jeter",
        "jeté"
    ],
    "PREZ/EUD/APBS/*EUFL": [
        "présidentiel",
        "présidentielle"
    ],
    "KOEPB/T*EUB/APBT/AL": [
        "continental",
        "continentale"
    ],
    "KOEPBT/*EUB/APBT/AL": [
        "continental",
        "continentale"
    ],
    "KOPBT/*EUB/APBT/AL": [
        "continental",
        "continentale"
    ],
    "ST*EUB/APBT/AL": [
        "continental",
        "continentale"
    ],
    "PRA*EUFPB/U": [
        "prévenu",
        "prévenue"
    ],
    "PHOPBG/O*L": [
        "mongol",
        "mongole"
    ],
    "KA*RB": [
        "carne",
        "cassis",
        "cabale",
        "kabbale"
    ],
    "AB/A*": [
        "ana",
        "abat",
        "ananas",
        "anas"
    ],
    "TPA*R": [
        "phare",
        "far",
        "fard",
        "fart",
        "fare"
    ],
    "PHO*R": [
        "mort",
        "mors",
        "more"
    ],
    "K*EUP": [
        "équipe",
        "kip",
        "skip"
    ],
    "P*EUT/PWOUL": [
        "pitbull",
        "pit-bull",
        "pit bull"
    ],
    "EUPB/PO*EUL": [
        "impoli",
        "impolie"
    ],
    "TA*PB": [
        "tant",
        "tan",
        "taon"
    ],
    "HRO*BG": [
        "loque",
        "alloc",
        "loch"
    ],
    "EUPB/PA*EUR": [
        "imper",
        "impaire",
        "impair"
    ],
    "KPWA*EUR": [
        "imper",
        "impaire",
        "impair",
        "ampère"
    ],
    "PA*EURPL": [
        "sperme",
        "perme",
        "perm"
    ],
    "PEFP/*E": [
        "péché",
        "pêcher",
        "pêché"
    ],
    "PAR/WH*U": [
        "parvenu",
        "parvenue"
    ],
    "TPOURB/*EU": [
        "fourbi",
        "fournie",
        "fourni",
        "fournil"
    ],
    "HOB/*EU": [
        "hobby",
        "honnie",
        "honni"
    ],
    "PHET/*EUS": [
        "métis",
        "métisse"
    ],
    "SA*EUR": [
        "cerf",
        "serf",
        "serre",
        "sert"
    ],
    "PWR*UT": [
        "brute",
        "brut"
    ],
    "KRA*BG": [
        "crack",
        "craque",
        "crac",
        "krach",
        "krak"
    ],
    "KPWORT/*E": [
        "importé",
        "emporté"
    ],
    "KPWORT/*ED": [
        "importée",
        "emportée"
    ],
    "AEUBG/EUPL/O*E": [
        "esquimau",
        "esquimaux"
    ],
    "PHAR/*EU": [
        "mari",
        "marri",
        "mary",
        "marrie"
    ],
    "PWAB/*EU": [
        "banni",
        "bannie",
        "babi"
    ],
    "KOUL/*ED": [
        "écoulée",
        "coulée"
    ],
    "SK*": [
        "shah",
        "conque",
        "chas",
        "chah",
        "schah"
    ],
    "HA*EU": [
        "haie",
        "haï",
        "hai",
        "haïe"
    ],
    "*FRB/EU": [
        "vernis",
        "vernie",
        "verni"
    ],
    "KAB/*EUB": [
        "cabine",
        "canine"
    ],
    "WHRAT/*EUL": [
        "volatil",
        "volatile"
    ],
    "R*EG/AOPBL": [
        "régional",
        "régionale"
    ],
    "KOUL/*E": [
        "écoulé",
        "coulé"
    ],
    "STKPHUB/*EU": [
        "démuni",
        "démunie"
    ],
    "PHAPL/*EU": [
        "mamie",
        "mammy",
        "mamy"
    ],
    "O*PB": [
        "on",
        "open"
    ],
    "KO*P": [
        "cop",
        "scope",
        "cops",
        "écope"
    ],
    "*EGS": [
        "aigri",
        "aigrie"
    ],
    "KHR*EUBG": [
        "clique",
        "click",
        "clic"
    ],
    "KOEPB/*FRBT/EU": [
        "converti",
        "convertie"
    ],
    "KOPB/*FRBT/EU": [
        "converti",
        "convertie"
    ],
    "S*FRBT/EU": [
        "converti",
        "convertie"
    ],
    "H*EB/RAO": [
        "hébreu",
        "hébreux"
    ],
    "TH*U": [
        "tenue",
        "ténu",
        "tenu",
        "ténue"
    ],
    "AE/UR/*EU": [
        "ahuri",
        "ahurie"
    ],
    "AUR/*EU": [
        "ahuri",
        "ahurie"
    ],
    "TKO*PB": [
        "dont",
        "dom",
        "don"
    ],
    "TPARS/*EU": [
        "farci",
        "farsi",
        "farcie"
    ],
    "PWRO*": [
        "bourreau",
        "broc",
        "bourreaux"
    ],
    "TR*EUB/U": [
        "tribu",
        "tribun",
        "tribut"
    ],
    "KUR/*EU": [
        "écurie",
        "curie",
        "curry"
    ],
    "*PBLG/EUB": [
        "jean",
        "djinn",
        "gin"
    ],
    "R*E": [
        "ré",
        "rez"
    ],
    "KOEPB/TRABGT/W*FL": [
        "contractuel",
        "contractuelle"
    ],
    "KOEPBT/RABGT/W*FL": [
        "contractuel",
        "contractuelle"
    ],
    "KOPBT/RABGT/W*FL": [
        "contractuel",
        "contractuelle"
    ],
    "STRABGT/W*FL": [
        "contractuel",
        "contractuelle"
    ],
    "TPHAZ/O*E": [
        "nasaux",
        "naseaux",
        "naseau"
    ],
    "THR*": [
        "telle",
        "till",
        "tell",
        "tél.",
        "tél",
        "talle"
    ],
    "TOB/*EUBG": [
        "tonic",
        "tonique"
    ],
    "PWR*U": [
        "brun",
        "bourru",
        "bru",
        "bourrue"
    ],
    "PHAB/O*UL": [
        "maboul",
        "maboule"
    ],
    "RA*PB": [
        "rang",
        "ran",
        "errant"
    ],
    "R*/W-LZ/AL": [
        "royal",
        "royale"
    ],
    "PWR*EU": [
        "bris",
        "brie",
        "bri"
    ],
    "KO*T": [
        "cote",
        "kot",
        "cotes",
        "cotte"
    ],
    "PH*EUR": [
        "mire",
        "mir",
        "myrrhe"
    ],
    "PWARG/O*": [
        "barjo",
        "barjot"
    ],
    "KART/*R": [
        "écarter",
        "carter",
        "quarter"
    ],
    "SHA*EUBG": [
        "chèque",
        "cheikh",
        "cheik",
        "scheik"
    ],
    "HRA*EUBG": [
        "laïque",
        "laïc",
        "lek"
    ],
    "HRET/R*E": [
        "illettré",
        "lettré"
    ],
    "KA*B": [
        "canne",
        "khan",
        "cab",
        "kan"
    ],
    "PWA*T": [
        "batte",
        "bath",
        "baht"
    ],
    "TK*EUG": [
        "ding",
        "dig",
        "digue"
    ],
    "KAP/O*": [
        "capot",
        "kapo",
        "capo",
        "capoc"
    ],
    "HRA*EUFT": [
        "lest",
        "laïcité",
        "leste"
    ],
    "KO*EUPL/OT": [
        "copilote",
        "co-pilote"
    ],
    "KHRA*EU": [
        "minerai",
        "colley",
        "collet",
        "claie"
    ],
    "HOPL/OS/K*S/UFL": [
        "homosexuel",
        "homosexuelle"
    ],
    "KPHA*EUR": [
        "commère",
        "khmère",
        "khmer"
    ],
    "TKPW*": [
        "j",
        "geai",
        "jais"
    ],
    "EUPBT/ROFRBT/*EU": [
        "introverti",
        "introvertie"
    ],
    "SPWROFRBT/*EU": [
        "introverti",
        "introvertie"
    ],
    "PHO*L": [
        "molle",
        "mole",
        "mol"
    ],
    "PA*EURS/APB": [
        "perçant",
        "persan"
    ],
    "PR*S/APB": [
        "perçant",
        "persan"
    ],
    "RA*BG": [
        "yack",
        "rack",
        "yak",
        "rac"
    ],
    "A/FR/AFRPBLG/*EU": [
        "affranchi",
        "affranchie"
    ],
    "AE/TPRAFRPBLG/*EU": [
        "affranchi",
        "affranchie"
    ],
    "SA*EUFP": [
        "sèche",
        "seiche",
        "sèche-cheveux"
    ],
    "WHO*E": [
        "finaux",
        "finaud"
    ],
    "KOBG/EUP/A*ER": [
        "coéquipier",
        "co-équipier",
        "coéquipière"
    ],
    "TKPWR*GS": [
        "grigri",
        "gri-gri",
        "gris-gris"
    ],
    "PW*EUG/O": [
        "bingo",
        "bigot",
        "bigo"
    ],
    "SHER/*EUFL": [
        "shérif",
        "chérif"
    ],
    "RA*D": [
        "rade",
        "rad",
        "radis"
    ],
    "PWO*E": [
        "beaux",
        "baux",
        "bau",
        "baud"
    ],
    "SA*EPB": [
        "sien",
        "cyan",
        "sciant"
    ],
    "SKWR*R/EUBG/AB": [
        "jerrycan",
        "jerricane",
        "jerrican"
    ],
    "KAR/*EU": [
        "carie",
        "kari",
        "carry",
        "cari",
        "cary",
        "équarri",
        "équarrie"
    ],
    "R*P/APBT/EU": [
        "repenti",
        "repentie"
    ],
    "PWOU/EU/*EU": [
        "bouillie",
        "bouilli"
    ],
    "*FRBT/EUBG/AL": [
        "verticale",
        "vertical"
    ],
    "A*E/PHOB/RABG": [
        "ammoniaque",
        "ammoniac"
    ],
    "APL/O*B/RABG": [
        "ammoniaque",
        "ammoniac"
    ],
    "TPHAPBT/*EU": [
        "nanti",
        "nantie"
    ],
    "O*R": [
        "or",
        "ort",
        "ord",
        "ore"
    ],
    "ROS/PW*EUFL": [
        "rosbif",
        "roast beef",
        "roast-beef"
    ],
    "KAO*": [
        "queue",
        "chao",
        "chaos",
        "cahot",
        "k-o"
    ],
    "EUPB/PR*R/AL": [
        "impérial",
        "impériale"
    ],
    "KPWR*R/AL": [
        "impérial",
        "impériale"
    ],
    "PA*EUB": [
        "peine",
        "pêne",
        "penne"
    ],
    "APBT/*EUFL": [
        "anti-vol",
        "antivol"
    ],
    "SPW*EUFL": [
        "anti-vol",
        "antivol"
    ],
    "KPH*UPBL": [
        "communal",
        "communale"
    ],
    "PHA/AR/APBLG/A*": [
        "maharadjah",
        "maharadja",
        "maharajah",
        "maharaja"
    ],
    "O*RBG": [
        "orque",
        "ocre"
    ],
    "PO*EU": [
        "pois",
        "poix",
        "pouah"
    ],
    "PR*EUFL": [
        "périph",
        "périf"
    ],
    "K*EUFL": [
        "kif",
        "skiff"
    ],
    "TRA*S": [
        "trace",
        "thrace",
        "terrasse"
    ],
    "TO*R": [
        "tort",
        "tore",
        "tors"
    ],
    "T*S/EUG/AB": [
        "tzigane",
        "tsigane"
    ],
    "PWA*EUG": [
        "beige",
        "bègue"
    ],
    "H*LZ/TAEUBG": [
        "high tech",
        "high-tech"
    ],
    "KAFP/A*EUR": [
        "kasher",
        "kascher",
        "casher",
        "cascher",
        "cachère"
    ],
    "PHO*PBD/RAL": [
        "mondial",
        "mondiale"
    ],
    "ROET/*EU": [
        "rôti",
        "rôtie"
    ],
    "SHRA*EUBGT": [
        "select",
        "sélecte",
        "sélect"
    ],
    "APBT/*EUG/APBG": [
        "anti-gang",
        "antigang"
    ],
    "SPW*EUG/APBG": [
        "anti-gang",
        "antigang"
    ],
    "AE/*ER/OP/AS/RAL": [
        "aérospatial",
        "aérospatiale"
    ],
    "A*ER/OP/AS/RAL": [
        "aérospatial",
        "aérospatiale"
    ],
    "TPREUL/*PBS": [
        "freelance",
        "free-lance"
    ],
    "TPR*EUL/APBS": [
        "freelance",
        "free-lance"
    ],
    "TPR*EUL/APBSZ": [
        "freelance",
        "free-lance"
    ],
    "PAFT/O*R/AL": [
        "pastoral",
        "pastorale"
    ],
    "PAFT/O*RL": [
        "pastoral",
        "pastorale"
    ],
    "RA*EU": [
        "rai",
        "rets",
        "raie",
        "raïs"
    ],
    "STPH*EUFL": [
        "snif",
        "sniff"
    ],
    "PWAZ/EUL/*EUBG": [
        "basilic",
        "basilique"
    ],
    "KAR/A*EUB": [
        "karen",
        "carène",
        "caraïbe"
    ],
    "SHA*EUD/AOFR": [
        "chef-d'oeuvre",
        "chef-d'oeuvres",
        "chefs-d'oeuvre"
    ],
    "KO*BG/AR": [
        "coquard",
        "coquart",
        "cocard"
    ],
    "TPHREUP/*E": [
        "flipper",
        "flippé"
    ],
    "HEUP/*EU": [
        "hippie",
        "hippy"
    ],
    "EUR/ABG/A*EPB": [
        "irakien",
        "iraquien"
    ],
    "KAT/R*F/EUPB": [
        "quatre-vingt",
        "quatre-vingt-treize",
        "quatre-vingts",
        "quatre-vingt-trois"
    ],
    "RA*PL": [
        "rame",
        "ram",
        "rams"
    ],
    "TO*BG/AR": [
        "tocard",
        "toquard"
    ],
    "WEB/*E": [
        "vénéneuse",
        "veiné",
        "vénéneux"
    ],
    "A*E/SOS/RAL": [
        "asocial",
        "asociale"
    ],
    "AS/O*S/RAL": [
        "asocial",
        "asociale"
    ],
    "KAB/A*": [
        "cabas",
        "canna",
        "kana",
        "khanat"
    ],
    "KAZ/A*BG": [
        "casaque",
        "kazakh"
    ],
    "HRA*EUT/OPB": [
        "laiton",
        "letton"
    ],
    "PORT/KHR*E": [
        "porte-clés",
        "porte-clé",
        "porte-clefs",
        "porte-clef"
    ],
    "KOL/A*EUR": [
        "colère",
        "scolaire"
    ],
    "PWAL/A*EUZ": [
        "balèze",
        "balaise"
    ],
    "TKEUG/*EUT/AL": [
        "digital",
        "digitale"
    ],
    "SKWRA*R": [
        "jarre",
        "jars",
        "jar"
    ],
    "HRUFT/R*E": [
        "illustré",
        "lustré"
    ],
    "RA*FL": [
        "rafle",
        "raff",
        "raval"
    ],
    "TR*PBS": [
        "transe",
        "trans"
    ],
    "TRA*PBS": [
        "transe",
        "trans"
    ],
    "*FRB": [
        "vers",
        "vair",
        "verne"
    ],
    "AE/PH*EUBG/AL": [
        "amical",
        "amicale"
    ],
    "APL/*EUBG/AL": [
        "amical",
        "amicale"
    ],
    "SH*B/OBG": [
        "schnock",
        "chnoque",
        "schnoque"
    ],
    "RAD/*EUBG/AL": [
        "radical",
        "radicale"
    ],
    "R*U/RAL": [
        "rural",
        "rurale"
    ],
    "R*URL": [
        "rural",
        "rurale"
    ],
    "HREG/*R": [
        "léguer",
        "alléguer",
        "alléger"
    ],
    "TKO*RS/HR": [
        "dorsal",
        "dorsale"
    ],
    "*BGS/TRAFRBT/EU": [
        "extraverti",
        "extravertie"
    ],
    "KP*T/RAFRBT/EU": [
        "extraverti",
        "extravertie"
    ],
    "SKWREPL/O*E": [
        "gémeau",
        "gémeaux"
    ],
    "PHA*BG": [
        "mac",
        "mach",
        "maque"
    ],
    "PHAD/PHOEUZ/*FL": [
        "mademoiselle",
        "mlle"
    ],
    "PO*L/ABG": [
        "polack",
        "polak",
        "polaque"
    ],
    "PA*T": [
        "patte",
        "spath",
        "pat"
    ],
    "TO*PL": [
        "tom",
        "tomme",
        "tome"
    ],
    "TR*EUBG": [
        "trique",
        "tric",
        "trick"
    ],
    "KA/A*E": [
        "caillé",
        "écaillé",
        "écailler"
    ],
    "*BGS/TRAS/APBS/OR/EUFL": [
        "extrasensoriel",
        "extra-sensoriel",
        "extrasensorielle",
        "extra-sensorielle"
    ],
    "KP*T/RAS/APBS/OR/EUFL": [
        "extrasensoriel",
        "extra-sensoriel",
        "extrasensorielle",
        "extra-sensorielle"
    ],
    "PHAB/RABG/OD/EPS/ES/*EUFL": [
        "maniaco-dépressif",
        "maniacodépressif"
    ],
    "K*T": [
        "compte",
        "scat",
        "équité"
    ],
    "STPHOB/*EU": [
        "snobinard",
        "snobinarde"
    ],
    "TAP/*EU": [
        "tapis",
        "tapie",
        "tapi"
    ],
    "EUFRPB/OPBD/EUGZ/*FL": [
        "inconditionnel",
        "inconditionnelle"
    ],
    "EUPB/KOEPBD/EUGZ/*FL": [
        "inconditionnel",
        "inconditionnelle"
    ],
    "TPHA*FL": [
        "naval",
        "navale",
        "navel"
    ],
    "K*EUB": [
        "skin",
        "équin",
        "quine",
        "équine"
    ],
    "AE/RA*EPB": [
        "aryen",
        "arien"
    ],
    "AR/A*EPB": [
        "aryen",
        "arien"
    ],
    "PWO*URD": [
        "bourde",
        "boudeur"
    ],
    "KAB/O*": [
        "canot",
        "canonnade",
        "cabot"
    ],
    "SHAPL/A*B": [
        "chaman",
        "chamane",
        "shaman"
    ],
    "SKPHA*B": [
        "chaman",
        "chamane",
        "shaman"
    ],
    "SHO*UR/A": [
        "chouia",
        "chouya",
        "chouïa"
    ],
    "KO*B": [
        "conne",
        "cob",
        "scone"
    ],
    "KO*B/AR": [
        "connard",
        "conard"
    ],
    "KUBG/*U": [
        "cucul",
        "cul-cul",
        "cucu"
    ],
    "STKOUL/*R": [
        "dessoûler",
        "dessouler",
        "dessaouler"
    ],
    "TKPWR*L": [
        "grill",
        "graal",
        "gril"
    ],
    "SKWRAPL/AEUBG/*EUPB": [
        "jamaïcain",
        "jamaïquain"
    ],
    "KAFL/TA*PB": [
        "cafetan",
        "kaftan",
        "caftan"
    ],
    "HROBG/*UGS": [
        "élocution",
        "locution",
        "allocution"
    ],
    "PHAR/AO*L": [
        "mariolle",
        "mariol",
        "mariole"
    ],
    "TPHEUG/ER/A*EPB": [
        "nigérian",
        "nigérien"
    ],
    "PABGS/O*PB": [
        "paxon",
        "packson",
        "pacson",
        "paqson"
    ],
    "P*LZ/AR": [
        "pillard",
        "paillard"
    ],
    "KA*RT": [
        "carte",
        "quarte",
        "kart",
        "karité"
    ],
    "K*EUT": [
        "quitte",
        "skeet",
        "kit"
    ],
    "S*E/APB": [
        "céans",
        "séant"
    ],
    "T*FL": [
        "telle",
        "tél",
        "tell"
    ],
    "ULT/RAF/AOL/A*EU": [
        "ultraviolet",
        "ultra-violets",
        "ultra-violet"
    ],
    "HRA*RG": [
        "large",
        "élagueur",
        "largue"
    ],
    "PWA*U": [
        "bahut",
        "buis",
        "bât"
    ],
    "*RB": [
        "ci",
        "cis",
        "bale"
    ],
    "AFRPL/*EU": [
        "ampli",
        "emplie",
        "empli"
    ],
    "KPWHR*EU": [
        "ampli",
        "emplie",
        "empli",
        "embellie"
    ],
    "APBT/R*G/AFRB": [
        "entrejambe",
        "entre-jambe",
        "entre-jambes"
    ],
    "SPWR*G/AFRB": [
        "entrejambe",
        "entre-jambe",
        "entre-jambes"
    ],
    "TPHRA*": [
        "flat",
        "fla",
        "fellah"
    ],
    "TPRA*EU": [
        "frais",
        "frai",
        "fret"
    ],
    "HREUT/WAB/A*EPB": [
        "lituanien",
        "lithuanien"
    ],
    "PHAO*US": [
        "maousse",
        "mahousse",
        "maous"
    ],
    "PHAPLZ/*FL": [
        "mam'selle",
        "mam'zelle",
        "mamzelle"
    ],
    "PHAPLZ/A*EUL": [
        "mam'selle",
        "mam'zelle",
        "mamzelle"
    ],
    "P*EUT/SHOUB": [
        "pitchoun",
        "pitchoune"
    ],
    "RAG/A*": [
        "raga",
        "raja",
        "rajah"
    ],
    "SHRA*": [
        "cela",
        "salat",
        "cella"
    ],
    "SAPBS/KR*EU": [
        "sanskrit",
        "sanscrit"
    ],
    "PEUR/*EUT": [
        "pyrite",
        "spirite"
    ],
    "*TS/AER": [
        "trier",
        "strier",
        "terrier"
    ],
    "TA*FL": [
        "taffe",
        "tavel",
        "taf"
    ],
    "TR*EU": [
        "tri",
        "terril",
        "terri"
    ],
    "PW*EUFL": [
        "biffe",
        "bif"
    ],
    "KALS/*EUFL": [
        "calcif",
        "calecif"
    ],
    "A*EUS": [
        "s",
        "esse",
        "est-ce",
        "ès"
    ],
    "TPO*BG/AL": [
        "focal",
        "focale"
    ],
    "AEUS/KR*EUPL": [
        "escrime",
        "ice-cream",
        "ice cream"
    ],
    "HREG/EUT/*EUPLT": [
        "légitimité",
        "légitimant",
        "illégitimité"
    ],
    "PHARP/*EU": [
        "maori",
        "maorie"
    ],
    "OUT/R*PL/AEUR": [
        "outre-mer",
        "outremer"
    ],
    "PAG/A*LZ": [
        "pagaille",
        "pagaye",
        "pagaïe"
    ],
    "PARS/*EU": [
        "par-ci",
        "parsi"
    ],
    "PO*FT/TPHAT/AL": [
        "post-natal",
        "postnatal",
        "post-natale",
        "postnatale"
    ],
    "SH*L/AO": [
        "chleuh",
        "schleu"
    ],
    "SHRA*ER": [
        "cellier",
        "sellier",
        "salière"
    ],
    "TOEL/A*ER": [
        "taulier",
        "tôlier",
        "taulière"
    ],
    "W*EUD/AOUBG/HRAOB": [
        "vidéoclub",
        "vidéo-club"
    ],
    "*ET/AL": [
        "étal",
        "étale"
    ],
    "APL/O*PB": [
        "aplomb",
        "amont"
    ],
    "APBT/EUBG/OPL/UB/*EUFT": [
        "anticommuniste",
        "anti-communiste"
    ],
    "SPWEUBG/OPL/UB/*EUFT": [
        "anticommuniste",
        "anti-communiste"
    ],
    "APBT/EUPL/*EUT": [
        "anti-mite",
        "antimite"
    ],
    "SPWEUPL/*EUT": [
        "anti-mite",
        "antimite"
    ],
    "AE/WR*PB": [
        "arche",
        "archie",
        "archi"
    ],
    "A*FRPB": [
        "arche",
        "archie",
        "archi"
    ],
    "PWARB/*U": [
        "barbu",
        "barbue"
    ],
    "PWHRO*": [
        "ballot",
        "bellot",
        "blot"
    ],
    "PWO*B/AR": [
        "bobard",
        "bonard",
        "bonnard"
    ],
    "PWR*LZ/AR": [
        "braillard",
        "briard"
    ],
    "PWO*ULD/OG": [
        "bouledogue",
        "bull-dog",
        "bulldog"
    ],
    "PW*UT": [
        "but",
        "bute",
        "butte"
    ],
    "KA*FL": [
        "cavale",
        "caf"
    ],
    "KAR/ABGT/ER/*EUFL": [
        "caractériel",
        "caractérielle"
    ],
    "KAR/A*ER": [
        "carier",
        "carrier",
        "carrière"
    ],
    "SHA*EPB": [
        "chien",
        "chiens",
        "chiant"
    ],
    "KO*R/AL": [
        "chorale",
        "choral"
    ],
    "KO*RL": [
        "chorale",
        "choral"
    ],
    "KORB/*U": [
        "cornu",
        "cornue"
    ],
    "KOURS/*EURBG/AU": [
        "court-circuit",
        "court-circuits"
    ],
    "KRO*EU": [
        "croix",
        "croît",
        "courroie"
    ],
    "KULT/*U/RAL": [
        "sculptural",
        "cultural",
        "sculpturale"
    ],
    "KULT/*URL": [
        "sculptural",
        "cultural",
        "sculpturale"
    ],
    "SPW*": [
        "ante",
        "ente",
        "inde"
    ],
    "TPA*ER": [
        "fier",
        "fillér",
        "fière"
    ],
    "TPO*R": [
        "fort",
        "fors",
        "for"
    ],
    "TPR*EUT": [
        "frite",
        "fritte",
        "ferrite"
    ],
    "TP*EU": [
        "fi",
        "fy",
        "phi"
    ],
    "TKPWO*UT/AOZ": [
        "goûteuse",
        "goutteuse"
    ],
    "TKPWO*UT/AO": [
        "goûteux",
        "goutteux"
    ],
    "HAFP/*EUFP": [
        "haschich",
        "hachisch",
        "haschisch"
    ],
    "SPWA*U": [
        "enduit",
        "induit"
    ],
    "SKWRA*FL": [
        "javel",
        "javelle",
        "jaffe"
    ],
    "SKWRO*EUL": [
        "joli",
        "jolie"
    ],
    "HRA*EPB": [
        "lien",
        "liant"
    ],
    "HR*EUPLT": [
        "limité",
        "liman",
        "illimité"
    ],
    "KH*UT": [
        "minute",
        "mn"
    ],
    "PHO*L/AS": [
        "mollasse",
        "molasse"
    ],
    "TPHE/APBD/AEURT/AL/A*EPB": [
        "néandertalien",
        "néanderthalien"
    ],
    "PA*RBL": [
        "pare-balles",
        "pare-balle"
    ],
    "PROD/*EUG": [
        "prodige",
        "prodigue"
    ],
    "S*EUT": [
        "site",
        "psitt",
        "scythe"
    ],
    "KA*EUT": [
        "quête",
        "quette",
        "ket"
    ],
    "R*L/AE": [
        "relié",
        "rallié"
    ],
    "RAPL/A*": [
        "yama",
        "ramas",
        "raplapla"
    ],
    "REFL/HRA*EUBGS": [
        "réflexe",
        "reflex"
    ],
    "REZ/*EUD/APB": [
        "résident",
        "résidant"
    ],
    "SH*B/OUFL": [
        "chnouf",
        "schnouff",
        "schnouf"
    ],
    "SEUPB/PHR*EUFT": [
        "simplicité",
        "simpliste"
    ],
    "SHRA*F": [
        "salve",
        "slave"
    ],
    "TA*EUBG": [
        "tek",
        "tec",
        "teck"
    ],
    "WA*EURBL": [
        "verbal",
        "vernal",
        "verbale"
    ],
    "AB/AS/RA*L": [
        "abbatial",
        "abbatiale"
    ],
    "A*E/PWAS/RAL": [
        "abbatial",
        "abbatiale"
    ],
    "A*E/KRU": [
        "accru",
        "accrue"
    ],
    "ARBG/*U": [
        "accru",
        "accrue"
    ],
    "HRUZ/*EUF": [
        "élusive",
        "allusive"
    ],
    "AE/HRA*EUZ": [
        "alaise",
        "alèze",
        "alèse"
    ],
    "AL/A*EUZ": [
        "alaise",
        "alèze",
        "alèse"
    ],
    "APBT/EU/AER/A*EPB": [
        "antiaérien",
        "anti-aérien"
    ],
    "SPWEU/AER/A*EPB": [
        "antiaérien",
        "anti-aérien"
    ],
    "PWHRA*PB": [
        "blanc",
        "ballant"
    ],
    "PWEZ/A*EUFL": [
        "bésef",
        "bezef",
        "bézef"
    ],
    "PWEUFLT/A*EUBG": [
        "bifteck",
        "biftèque",
        "beefsteak"
    ],
    "PW*EUZ/PWS": [
        "business",
        "biseness",
        "bizness",
        "bisness"
    ],
    "PW*EUTS": [
        "bitter",
        "bistre",
        "biture"
    ],
    "PWO*RT/SH": [
        "bortsch",
        "borchtch",
        "bortch"
    ],
    "KAG/O*": [
        "cageot",
        "cagot"
    ],
    "KAP/OUT/SH*EUB/O": [
        "cappuccino",
        "capucino",
        "capuccino"
    ],
    "KAT/A*R": [
        "catarrhe",
        "cathare"
    ],
    "SHA*PB": [
        "champ",
        "chand",
        "chant"
    ],
    "SH*T/EUPL/EU": [
        "ch'timi",
        "chtimi"
    ],
    "KHRO*BG": [
        "cloque",
        "cloc",
        "colloque"
    ],
    "KHR*EG/RAL": [
        "collégial",
        "collégiale"
    ],
    "KOEPB/TR*FP/APB": [
        "contrechamp",
        "contre-chant",
        "contre-champ"
    ],
    "KOEPBT/R*FP/APB": [
        "contrechamp",
        "contre-chant",
        "contre-champ"
    ],
    "KOPBT/R*FP/APB": [
        "contrechamp",
        "contre-chant",
        "contre-champ"
    ],
    "STR*FP/APB": [
        "contrechamp",
        "contre-chant",
        "contre-champ"
    ],
    "KOS/*U": [
        "cossu",
        "cossus",
        "cossue"
    ],
    "TKA*B": [
        "dan",
        "dabe",
        "dab"
    ],
    "STKA*EUR": [
        "désert",
        "desserre",
        "dessert"
    ],
    "STK*FRB/APB": [
        "déversant",
        "desservant"
    ],
    "TKEUG/A*EUFT": [
        "digest",
        "digeste"
    ],
    "STK*G/OUT/APBT": [
        "dégoûtante",
        "dégouttante"
    ],
    "KPW*U": [
        "imbu",
        "embu",
        "imbue"
    ],
    "APB/TKPWHR*EUFP": [
        "angliche",
        "engliche"
    ],
    "SPWAPBD/A*PB": [
        "intendant",
        "entendant"
    ],
    "AEUTS/ET/*ER/A": [
        "etc",
        "etcetera",
        "etc."
    ],
    "TPRO*": [
        "fourreau",
        "ferro",
        "fourreaux"
    ],
    "TKPWRA*FL": [
        "graphe",
        "gravelle",
        "graff"
    ],
    "HA*EUR": [
        "haïr",
        "haire",
        "hère"
    ],
    "KOR/*E": [
        "coré",
        "koré"
    ],
    "HRARBG/EUPL/AFT/*EU": [
        "lacrima-christi",
        "lacryma-christi",
        "lacryma christi"
    ],
    "PHAFL/AO*EU": [
        "mafieux",
        "maffieux"
    ],
    "PHA*R": [
        "marre",
        "mare"
    ],
    "PHAFT/A*R": [
        "mastard",
        "mastar"
    ],
    "PHR*EUPB": [
        "plein",
        "merrain",
        "plain"
    ],
    "PHO*D": [
        "mode",
        "mod"
    ],
    "TPHARG/EUL/*E": [
        "narguilé",
        "narghileh",
        "narghilé"
    ],
    "TPHAOUG/OT/*EUBG": [
        "néogothique",
        "néo-gothique"
    ],
    "PR*E": [
        "pré",
        "perré"
    ],
    "PAO*L": [
        "peul",
        "peulh",
        "peuhl"
    ],
    "PHRA*EU": [
        "plaie",
        "plet",
        "play"
    ],
    "PROP/ORGZ/*FL": [
        "proportionnel",
        "proportionnelle"
    ],
    "PRE/ET/ABL/*EU": [
        "préétabli",
        "pré-établi",
        "préétablie"
    ],
    "PA*U": [
        "puis",
        "puy",
        "pât"
    ],
    "RO*UFL": [
        "rough",
        "rouf",
        "roof"
    ],
    "R*EG/AL": [
        "régal",
        "régale"
    ],
    "SHAFRP/O*EUPB": [
        "shampooing",
        "schampooing",
        "shampoing"
    ],
    "PA*RT": [
        "parité",
        "sparte",
        "parthe"
    ],
    "S*EFL/AR/AD": [
        "séfarade",
        "sépharade"
    ],
    "T*EUFP/AORT": [
        "t-shirt",
        "ticheurte",
        "tee-shirt"
    ],
    "WAO*BG": [
        "vioque",
        "viocque",
        "vioc"
    ],
    "APL/A*": [
        "amas",
        "à-plat",
        "aplat"
    ]
}